{
  "_note": "Block-2 Step-4 progress: Pine signal SET extracted from instrumented fx_chain_validate.pine (FX Chain Validate) on CAPITALCOM:GBPUSD 5m. Used as the Pine side of the MENGEN-Abgleich vs scripts/fx_whole_chain.py Python reference. Next session: capture 5m>=450 / 1h>=250 / 4h>=200 concurrent (window must cover these signals + >=250 bars warmup), run fx_whole_chain.py, compare SET first.",
  "symbol": "CAPITALCOM:GBPUSD",
  "tf": "5",
  "captured_utc_bar_window_5m": {"from": 1780615200, "to": 1780922700},
  "pine_sig_count_full_history": 40,
  "all_long": true,
  "comment_dir_size": "label text = time_ms|dir(1=long/-1=short)|size; all dir=1 (short is USDCHF-only, chart is GBPUSD)",
  "signals_unix_s": [
    {"t": 1778534100, "dir": 1, "size": 1.0},
    {"t": 1779054900, "dir": 1, "size": 1.0},
    {"t": 1779225600, "dir": 1, "size": 0.5},
    {"t": 1779400200, "dir": 1, "size": 1.5},
    {"t": 1779717000, "dir": 1, "size": 0.5},
    {"t": 1779717300, "dir": 1, "size": 0.5},
    {"t": 1779717600, "dir": 1, "size": 0.5},
    {"t": 1779717900, "dir": 1, "size": 0.5},
    {"t": 1779718200, "dir": 1, "size": 0.5},
    {"t": 1779718500, "dir": 1, "size": 0.5},
    {"t": 1779743100, "dir": 1, "size": 1.5},
    {"t": 1779743400, "dir": 1, "size": 1.5},
    {"t": 1779743700, "dir": 1, "size": 1.5},
    {"t": 1779744000, "dir": 1, "size": 1.5},
    {"t": 1779744300, "dir": 1, "size": 1.5},
    {"t": 1779744600, "dir": 1, "size": 1.5},
    {"t": 1779744900, "dir": 1, "size": 1.5},
    {"t": 1779745200, "dir": 1, "size": 1.5},
    {"t": 1779745500, "dir": 1, "size": 1.5},
    {"t": 1779745800, "dir": 1, "size": 1.5},
    {"t": 1780261800, "dir": 1, "size": 1.0},
    {"t": 1780262400, "dir": 1, "size": 1.0},
    {"t": 1780263900, "dir": 1, "size": 1.5},
    {"t": 1780264200, "dir": 1, "size": 1.0},
    {"t": 1780264500, "dir": 1, "size": 1.5},
    {"t": 1780349400, "dir": 1, "size": 1.5},
    {"t": 1780350900, "dir": 1, "size": 1.0},
    {"t": 1780521600, "dir": 1, "size": 1.0},
    {"t": 1780523700, "dir": 1, "size": 1.5},
    {"t": 1780578600, "dir": 1, "size": 0.5},
    {"t": 1780610100, "dir": 1, "size": 1.5},
    {"t": 1780866000, "dir": 1, "size": 1.0},
    {"t": 1780866300, "dir": 1, "size": 1.5},
    {"t": 1780866600, "dir": 1, "size": 1.5},
    {"t": 1780866900, "dir": 1, "size": 1.0},
    {"t": 1780867200, "dir": 1, "size": 1.5},
    {"t": 1780867500, "dir": 1, "size": 1.5},
    {"t": 1780867800, "dir": 1, "size": 1.5},
    {"t": 1780868100, "dir": 1, "size": 1.5},
    {"t": 1780868700, "dir": 1, "size": 1.5}
  ]
}
